gridmeta/__init__.py
gridmeta/json_utils.py
gridmeta/models.py
gridmeta/opendss.py
gridmeta/privacy.py
gridmeta/version.py
gridmeta/cli/cli.py
gridmeta/cli/converter.py
gridmeta/schemas/DehydrationMetadataV1.schema.json
gridmeta-1.0.2.dist-info/METADATA
gridmeta-1.0.2.dist-info/WHEEL
gridmeta-1.0.2.dist-info/entry_points.txt
gridmeta-1.0.2.dist-info/licenses/LICENSE
gridmeta-1.0.2.dist-info/RECORD
