Metadata-Version: 2.4
Name: gridmeta
Version: 1.0.2
Summary: A repository for extracting dehydrated metadata for distribution power grid model.
Project-URL: Documentation, https://github.com/grid-kitchen/grid-meta
Project-URL: Issues, https://github.com/grid-kitchen/grid-meta/issues
Project-URL: Source, https://github.com/grid-kitchen/grid-meta
Author-email: Kapil Duwadi <kapil.duwadi@pnnl.gov>, Kaustav Bhattacharjee <kaustav.bhattacharjee@pnnl.gov>, Alexander Anderson <Alexander.Anderson@pnnl.gov>, Rabayet Sadnan <rabayet.sadnan@pnnl.gov>
License-Expression: BSD-3-Clause
License-File: LICENSE
Classifier: Programming Language :: Python :: 3.11
Classifier: Programming Language :: Python :: 3.12
Classifier: Programming Language :: Python :: 3.13
Requires-Python: >=3.11
Requires-Dist: click~=8.2.1
Requires-Dist: datamodel-code-generator~=0.31.2
Requires-Dist: jsonschema~=4.24.0
Requires-Dist: opendssdirect-py~=0.9.4
Requires-Dist: pandas~=2.2.3
Requires-Dist: pydantic~=2.11.5
Requires-Dist: requests~=2.32.3
Provides-Extra: dev
Requires-Dist: pre-commit~=4.2.0; extra == 'dev'
Requires-Dist: pytest-cov~=7.0.0; extra == 'dev'
Requires-Dist: pytest-mock~=3.14.1; extra == 'dev'
Requires-Dist: pytest~=9.0.1; extra == 'dev'
Requires-Dist: ruff~=0.11.12; extra == 'dev'
Provides-Extra: doc
Requires-Dist: mdutils~=1.7.0; extra == 'doc'
Requires-Dist: mike~=2.1.3; extra == 'doc'
Requires-Dist: mkdocs-material~=9.6.14; extra == 'doc'
